[
  {
    "Name": "Terry Pratchett"
  },
  {
    "Name": "George R. R. Martin"
  },
  {
    "Name": "J. K. Rowling"
  },
  {
    "Name": "John R. R. Tolkien"
  },
  {
    "Name": "George Orwell"
  },
  {
    "Name": "Patrick Rothfuss"
  },
  {
    "Name": "Brandon Sanderson"
  },
  {
    "Name": "J.D. Salinger"
  },
  {
    "Name": "Andy Weir"
  },
  {
    "Name": "Umberto Eco"
  },
  {
    "Name": "Marcus Aurelius"
  },
  {
    "Name": "Stieg Larsson"
  },
  {
    "Name": "Blake Crouch"
  },
  {
    "Name": "Charles Duhigg"
  },
  {
    "Name": "Cormac McCarthy"
  },
  {
    "Name": "Neil Gaiman"
  }
]
